watchdock/__init__.py
watchdock/ai_processor.py
watchdock/config.py
watchdock/file_organizer.py
watchdock/gui.py
watchdock/gui_main.py
watchdock/main.py
watchdock/pending_actions.py
watchdock/watcher.py
watchdock-0.1.5.dist-info/licenses/LICENSE
watchdock-0.1.5.dist-info/METADATA
watchdock-0.1.5.dist-info/WHEEL
watchdock-0.1.5.dist-info/entry_points.txt
watchdock-0.1.5.dist-info/top_level.txt
watchdock-0.1.5.dist-info/RECORD
