Metadata-Version: 2.4
Name: watchdock
Version: 0.1.5
Summary: A local, self-hosted file monitoring and organization tool using AI
Home-page: https://github.com/Z-MarkUs/watchdock
Author: WatchDock Team
Author-email: hehan.zhao@outlook.com
License-Expression: MIT
Project-URL: Homepage, https://github.com/Z-MarkUs/watchdock
Project-URL: Documentation, https://github.com/Z-MarkUs/watchdock#readme
Project-URL: Repository, https://github.com/Z-MarkUs/watchdock
Project-URL: Issues, https://github.com/Z-MarkUs/watchdock/issues
Keywords: file-organization,ai,automation,file-management,watchdog
Classifier: Development Status :: 3 - Alpha
Classifier: Intended Audience :: End Users/Desktop
Classifier: Programming Language :: Python :: 3
Classifier: Programming Language :: Python :: 3.8
Classifier: Programming Language :: Python :: 3.9
Classifier: Programming Language :: Python :: 3.10
Classifier: Programming Language :: Python :: 3.11
Classifier: Programming Language :: Python :: 3.12
Classifier: Operating System :: OS Independent
Classifier: Topic :: System :: Filesystems
Classifier: Topic :: Utilities
Requires-Python: >=3.8
License-File: LICENSE
Requires-Dist: watchdog>=3.0.0
Requires-Dist: openai>=1.0.0
Requires-Dist: anthropic>=0.18.0
Provides-Extra: dev
Requires-Dist: pytest>=7.0; extra == "dev"
Requires-Dist: black>=23.0; extra == "dev"
Requires-Dist: flake8>=6.0; extra == "dev"
Dynamic: author-email
Dynamic: home-page
Dynamic: license-file
Dynamic: requires-python
